pendes/__init__.py
pendes-0.0.6.dist-info/LICENSE.txt
pendes-0.0.6.dist-info/METADATA
pendes-0.0.6.dist-info/WHEEL
pendes-0.0.6.dist-info/top_level.txt
pendes-0.0.6.dist-info/RECORD
