Metadata-Version: 2.1
Name: pendes
Version: 0.0.6
Summary: no description
Home-page: UNKNOWN
Author: Binod Kumar
Author-email: ilikehits1999@gmail.com
License: UNKNOWN
Platform: UNKNOWN
Classifier: Programming Language :: Python :: 3
Classifier: License :: OSI Approved :: MIT License
Classifier: Operating System :: OS Independent
Requires-Dist: pyperclip
